[
  {
    "id": "ice-2076173989391581195",
    "x_post_id": "2076173989391581195",
    "title": "ICE人员持续驻留底特律德尔伯恩，推动遣返非法移民",
    "summary": "ICE官员建议保持1000名特工驻守德尔伯恩，完成所有非法移民的遣返。",
    "content_type": "brief",
    "published_at": "2026-07-12T05:17:07.000Z",
    "updated_at": "2026-07-12T05:24:23.213Z",
    "url": "/news/ice/2026/07/12/ice-2076173989391581195.html",
    "source_name": "Bill Black",
    "source_type": "official",
    "agency": "ICE/HSI",
    "source_account": "BillBlack3a",
    "source_trust": 90,
    "source_url": "https://x.com/BillBlack3a/status/2076173989391581195",
    "official_url": "",
    "source_text": "@Chicago1Ray Keep 1000 ICE agents in Dearborn until all Illegals are deported. The Denaturalize the rest and deport them too",
    "dedupe_key": "text:26f3df19e0f331f193cb4b63",
    "image_url": "",
    "confidence": 90,
    "keywords": [
      "ICE",
      "遣返",
      "德尔伯恩",
      "非法移民"
    ],
    "enforcement_events": [],
    "state_codes": [],
    "event_metadata_checked_at": "2026-07-12T05:24:23.213Z"
  },
  {
    "id": "ice-2076173132361261523",
    "x_post_id": "2076173132361261523",
    "title": "公众呼吁加强ICE执法和遣返措施",
    "summary": "社交媒体发文呼吁停止福利滥用，加大ICE逮捕和遣返力度。",
    "content_type": "brief",
    "published_at": "2026-07-12T05:13:42.000Z",
    "updated_at": "2026-07-12T05:24:14.774Z",
    "url": "/news/ice/2026/07/12/ice-2076173132361261523.html",
    "source_name": "Silverlace",
    "source_type": "official",
    "agency": "ICE/HSI",
    "source_account": "Silverlace1956",
    "source_trust": 90,
    "source_url": "https://x.com/Silverlace1956/status/2076173132361261523",
    "official_url": "",
    "source_text": "@WHLeavitt A this is our country this invasion of 3rd world get over welfare illegals has got to stop and many things must be done to deport stop welfare Ice arrest and 24/7 airline deportation no exceptions",
    "dedupe_key": "text:87f2526c71956bf8b9381821",
    "image_url": "",
    "confidence": 90,
    "keywords": [
      "ICE",
      "遣返",
      "非法移民",
      "福利滥用",
      "执法"
    ],
    "enforcement_events": [],
    "state_codes": [],
    "event_metadata_checked_at": "2026-07-12T05:24:14.774Z"
  },
  {
    "id": "ice-2076171957612016020",
    "x_post_id": "2076171957612016020",
    "title": "ICE官员强调普通美国人生活无涉执法行动",
    "summary": "ICE官员表示普通美国人不会因特朗普政治立场受到ICE逮捕，媒体多报道极端事件。",
    "content_type": "brief",
    "published_at": "2026-07-12T05:09:02.000Z",
    "updated_at": "2026-07-12T05:24:03.547Z",
    "url": "/news/ice/2026/07/12/ice-2076171957612016020.html",
    "source_name": "Col1234567",
    "source_type": "official",
    "agency": "ICE/HSI",
    "source_account": "Col234567",
    "source_trust": 90,
    "source_url": "https://x.com/Col234567/status/2076171957612016020",
    "official_url": "",
    "source_text": "@MarkPoulose The average American is not tainted by trump , won't be arrested by ICE and just wants to have a peaceful life. But you do realise that the media only report the utter shitstorm that is what I mentioned as did you at the start of your interview answer",
    "dedupe_key": "text:cfcd7d5f031aba21093696dd",
    "image_url": "",
    "confidence": 90,
    "keywords": [
      "ICE",
      "执法",
      "美国民众",
      "媒体报道"
    ],
    "enforcement_events": [],
    "state_codes": [],
    "event_metadata_checked_at": "2026-07-12T05:24:03.547Z"
  },
  {
    "id": "ice-2076170672531767384",
    "x_post_id": "2076170672531767384",
    "title": "记者指出ICE拘留期间死亡人数激增，称白宫扩建秘密拘留中心并阻挠监督",
    "summary": "知名记者Ana Kasparian称特朗普政府期间ICE拘留死亡人数大幅增加，白宫扩建拘留中心并阻挠监督。",
    "content_type": "brief",
    "published_at": "2026-07-12T05:03:56.000Z",
    "updated_at": "2026-07-12T05:23:43.828Z",
    "url": "/news/ice/2026/07/12/ice-2076170672531767384.html",
    "source_name": "BRICS+TODAY",
    "source_type": "official",
    "agency": "ICE/HSI",
    "source_account": "Afrijustice4all",
    "source_trust": 90,
    "source_url": "https://x.com/Afrijustice4all/status/2076170672531767384",
    "official_url": "",
    "source_text": "🚨 DISGUSTING: Top journalist Ana Kasparian confirms deaths in ICE custody have absolutely skyrocketed under the Trump administration.\n\nThe White House is expanding these secretive detention centers while intentionally blocking all oversight to hide massive human rights abuses! https://t.co/JO0O243CVL",
    "dedupe_key": "text:c51b2ac6b4aba7ef00d141a9",
    "image_url": "https://pbs.twimg.com/amplify_video_thumb/2076170581158830080/img/w3XopgRDbeAj1o2e.jpg",
    "confidence": 90,
    "keywords": [
      "ICE",
      "拘留死亡",
      "特朗普政府",
      "白宫",
      "拘留中心",
      "人权"
    ],
    "enforcement_events": [],
    "state_codes": [],
    "event_metadata_checked_at": "2026-07-12T05:23:43.828Z"
  },
  {
    "id": "ice-2076170660582175045",
    "x_post_id": "2076170660582175045",
    "title": "州赦免与联邦移民执法带来不同结果",
    "summary": "一州赦免案例与联邦移民执法形成对比，凸显公众知情权的重要性。",
    "content_type": "brief",
    "published_at": "2026-07-12T05:03:53.000Z",
    "updated_at": "2026-07-12T05:23:39.294Z",
    "url": "/news/ice/2026/07/12/ice-2076170660582175045.html",
    "source_name": "Arrests",
    "source_type": "official",
    "agency": "ICE/HSI",
    "source_account": "Arrests8",
    "source_trust": 90,
    "source_url": "https://x.com/Arrests8/status/2076170660582175045",
    "official_url": "",
    "source_text": "@libsoftiktok This case shows how a state pardon and federal immigration enforcement can lead to very different outcomes. Public access to offender records remains important for transparency and community awareness: https://t.co/anfpEYtjy5",
    "dedupe_key": "text:ab25d4caa43346345b89568b",
    "image_url": "",
    "confidence": 85,
    "keywords": [
      "州赦免",
      "联邦移民执法",
      "透明度",
      "公众知情权"
    ],
    "enforcement_events": [],
    "state_codes": [],
    "event_metadata_checked_at": "2026-07-12T05:23:39.294Z"
  },
  {
    "id": "ice-2076169875567849973",
    "x_post_id": "2076169875567849973",
    "title": "墨西哥将特朗普时期ICE相关死伤案件诉诸法庭",
    "summary": "墨西哥对特朗普任内ICE执法相关死亡事件提起诉讼。",
    "content_type": "brief",
    "published_at": "2026-07-12T05:00:46.000Z",
    "updated_at": "2026-07-12T05:23:20.281Z",
    "url": "/news/ice/2026/07/12/ice-2076169875567849973.html",
    "source_name": "James Macfarlane",
    "source_type": "official",
    "agency": "ICE/HSI",
    "source_account": "JamesMa96327530",
    "source_trust": 90,
    "source_url": "https://x.com/JamesMa96327530/status/2076169875567849973",
    "official_url": "",
    "source_text": "HOLY SH*T! Mexico Takes Trump’s ICE Killings to Court https://t.co/gvimryAqSF via @YouTube",
    "dedupe_key": "text:da72c58ea28426bfb796776c",
    "image_url": "",
    "confidence": 85,
    "keywords": [
      "墨西哥",
      "特朗普",
      "ICE",
      "诉讼",
      "死伤"
    ],
    "enforcement_events": [],
    "state_codes": [],
    "event_metadata_checked_at": "2026-07-12T05:23:20.281Z"
  },
  {
    "id": "ice-2076169713554423817",
    "x_post_id": "2076169713554423817",
    "title": "ICE官员遭枪击呼吁迅速逮捕涉案人员",
    "summary": "有观点指出若有人枪击ICE官员，应立即逮捕相关嫌疑人。",
    "content_type": "brief",
    "published_at": "2026-07-12T05:00:07.000Z",
    "updated_at": "2026-07-12T05:23:17.638Z",
    "url": "/news/ice/2026/07/12/ice-2076169713554423817.html",
    "source_name": "Minerva Cespedes",
    "source_type": "official",
    "agency": "ICE/HSI",
    "source_account": "MinervaC17380",
    "source_trust": 90,
    "source_url": "https://x.com/MinervaC17380/status/2076169713554423817",
    "official_url": "",
    "source_text": "If one person shoots an ICE officer Nadler should be immediately arrested https://t.co/tglSTMDQOW",
    "dedupe_key": "text:847ec1e544a83f85e03bdeb2",
    "image_url": "",
    "confidence": 90,
    "keywords": [
      "ICE",
      "执法官员",
      "枪击",
      "逮捕"
    ],
    "enforcement_events": [],
    "state_codes": [],
    "event_metadata_checked_at": "2026-07-12T05:23:17.638Z"
  },
  {
    "id": "ice-2076169684408586651",
    "x_post_id": "2076169684408586651",
    "title": "墨西哥总统威胁对美提起诉讼引发新美国公民关注",
    "summary": "墨西哥总统克劳迪娅·谢因鲍姆威胁对美国提告，因一次致命ICE执法行动引发争议。",
    "content_type": "brief",
    "published_at": "2026-07-12T05:00:00.000Z",
    "updated_at": "2026-07-12T05:23:14.980Z",
    "url": "/news/ice/2026/07/12/ice-2076169684408586651.html",
    "source_name": "Christina Aguayo",
    "source_type": "official",
    "agency": "ICE/HSI",
    "source_account": "ChristinaNewstv",
    "source_trust": 90,
    "source_url": "https://x.com/ChristinaNewstv/status/2076169684408586651",
    "official_url": "",
    "source_text": "#new US citizens are calling for action against Mexico's President after she threatened to sue the United States over a de*dly ICE shooting of an illegal migrant from Mexico who was allegedly trying to k*ll federal agents\n\nPresident Claudia Sheinbaum saying on Thursday that her https://t.co/umuEQIaGKl",
    "dedupe_key": "text:97898c4635c563482d605a86",
    "image_url": "https://pbs.twimg.com/media/HM5bJO-boAAEgMy.jpg",
    "confidence": 90,
    "keywords": [
      "墨西哥总统",
      "ICE射击",
      "致命执法",
      "非法移民",
      "联邦执法人员"
    ],
    "enforcement_events": [
      {
        "event_type": "other",
        "people_count": null,
        "occurred_at": null,
        "time_precision": "unknown",
        "city": "",
        "state_code": "",
        "state_name": "",
        "location_text": "",
        "confidence": 85,
        "source_excerpt": "a deadly ICE shooting of an illegal migrant from Mexico who was allegedly trying to kill federal agents"
      }
    ],
    "state_codes": [],
    "event_metadata_checked_at": "2026-07-12T05:23:14.980Z"
  },
  {
    "id": "ice-2076167871001198938",
    "x_post_id": "2076167871001198938",
    "title": "ICE将对非法选票寄送行为采取遣返行动",
    "summary": "ICE将遣返涉非法选票寄送的非美国公民，案件引发关注。",
    "content_type": "brief",
    "published_at": "2026-07-12T04:52:48.000Z",
    "updated_at": "2026-07-12T05:22:53.396Z",
    "url": "/news/ice/2026/07/12/ice-2076167871001198938.html",
    "source_name": "Jim Koon",
    "source_type": "official",
    "agency": "ICE/HSI",
    "source_account": "koon_jim98411",
    "source_trust": 90,
    "source_url": "https://x.com/koon_jim98411/status/2076167871001198938",
    "official_url": "",
    "source_text": "@JimWalshLD19 We will know when they are deported by ICE.  Then Hobbs will have to explain to Harmeet why he is sending ballots in the mail to a non US citizen in a federal election and allowing this garbage.",
    "dedupe_key": "text:af4490656208bce1d9244657",
    "image_url": "",
    "confidence": 95,
    "keywords": [
      "遣返",
      "选票",
      "非美国公民",
      "霍布斯",
      "联邦选举"
    ],
    "enforcement_events": [
      {
        "event_type": "removal",
        "people_count": null,
        "occurred_at": null,
        "time_precision": "unknown",
        "city": "Hobbs",
        "state_code": "NM",
        "state_name": "New Mexico",
        "location_text": "新墨西哥州霍布斯市",
        "confidence": 90,
        "source_excerpt": "We will know when they are deported by ICE."
      }
    ],
    "state_codes": [
      "NM"
    ],
    "event_metadata_checked_at": "2026-07-12T05:22:53.396Z"
  },
  {
    "id": "ice-2076167547917840771",
    "x_post_id": "2076167547917840771",
    "title": "国会共和党阻挠调查一名休斯顿男子被ICE致死事件",
    "summary": "国会部分共和党议员阻止对休斯顿一名无辜男子被ICE杀害事件的调查。",
    "content_type": "brief",
    "published_at": "2026-07-12T04:51:31.000Z",
    "updated_at": "2026-07-12T05:22:44.450Z",
    "url": "/news/ice/2026/07/12/ice-2076167547917840771.html",
    "source_name": "Emoluments Clause",
    "source_type": "media",
    "agency": "ICE",
    "source_account": "Emolclause",
    "source_trust": 82,
    "source_url": "https://x.com/Emolclause/status/2076167547917840771",
    "official_url": "",
    "source_text": "Let that sink in. Repubs in Congress are BLOCKING efforts to investigate the killing of an innocent Houston man by ICE—somebody who was not even the target of the ICE operation 🤦‍♀️",
    "dedupe_key": "text:7cad974a426f6e22d5a9ef97",
    "image_url": "",
    "confidence": 90,
    "keywords": [
      "ICE",
      "调查阻挠",
      "休斯顿",
      "无辜死亡",
      "国会共和党"
    ],
    "enforcement_events": [],
    "state_codes": [],
    "event_metadata_checked_at": "2026-07-12T05:22:44.450Z"
  },
  {
    "id": "ice-2076167348541677787",
    "x_post_id": "2076167348541677787",
    "title": "堪萨斯城警方配合ICE行动，找回多名失踪儿童",
    "summary": "堪萨斯城地区开展为期一年的行动，重点保护人群安全，找回多名当地失踪儿童。",
    "content_type": "brief",
    "published_at": "2026-07-12T04:50:43.000Z",
    "updated_at": "2026-07-12T05:22:36.210Z",
    "url": "/news/ice/2026/07/12/ice-2076167348541677787.html",
    "source_name": "The Bruiser",
    "source_type": "media",
    "agency": "ICE",
    "source_account": "DrHoosierHermit",
    "source_trust": 82,
    "source_url": "https://x.com/DrHoosierHermit/status/2076167348541677787",
    "official_url": "",
    "source_text": "This happened during a broader operation, with planning spanning about a year, focused on protecting crowds and combating exploitation around World Cup events in the Kansas City area.\n\nThe children recovered are mostly local runaways reported missing by families or caregivers.",
    "dedupe_key": "text:90fbacc16a86c4580e09ef6a",
    "image_url": "",
    "confidence": 90,
    "keywords": [
      "ICE",
      "堪萨斯城",
      "失踪儿童",
      "人口剥削",
      "世界杯"
    ],
    "enforcement_events": [],
    "state_codes": [],
    "event_metadata_checked_at": "2026-07-12T05:22:36.210Z"
  },
  {
    "id": "ice-2076166737796747285",
    "x_post_id": "2076166737796747285",
    "title": "斯里兰卡瓦特拉一女子因持有冰毒和海洛因被捕",
    "summary": "斯里兰卡瓦特拉警方逮捕一名女子，查获冰毒与海洛因。",
    "content_type": "brief",
    "published_at": "2026-07-12T04:48:18.000Z",
    "updated_at": "2026-07-12T05:22:19.096Z",
    "url": "/news/ice/2026/07/12/ice-2076166737796747285.html",
    "source_name": "Newsfirst.lk Sri Lanka",
    "source_type": "official",
    "agency": "ICE/HSI",
    "source_account": "NewsfirstSL",
    "source_trust": 90,
    "source_url": "https://x.com/NewsfirstSL/status/2076166737796747285",
    "official_url": "",
    "source_text": "Woman Arrested in Wattala Over Possession of Ice and Heroin\n\nDetails: https://t.co/qBja5SXnAd\n\n#Newsfirst #News1st #NewsfirstEnglish #SriLankaNews #CrimeNews #DrugBust #NarcoticsRaid #PoliceNarcoticsBureau #Wattala #HeroinSeized #IceNarcotics #SriLankaPolice #PoliceInvestigation https://t.co/JWZFmSCHwa",
    "dedupe_key": "text:64827f1d48435db9ca389bf6",
    "image_url": "https://pbs.twimg.com/media/HNAF9NRaMAAfqZj.jpg",
    "confidence": 95,
    "keywords": [
      "逮捕",
      "冰毒",
      "海洛因",
      "缉毒",
      "斯里兰卡",
      "瓦特拉"
    ],
    "enforcement_events": [
      {
        "event_type": "arrest",
        "people_count": 1,
        "occurred_at": "2026-07-12T04:48:18.000Z",
        "time_precision": "second",
        "city": "Wattala",
        "state_code": "",
        "state_name": "",
        "location_text": "斯里兰卡瓦特拉",
        "confidence": 95,
        "source_excerpt": "Woman Arrested in Wattala Over Possession of Ice and Heroin"
      }
    ],
    "state_codes": [],
    "event_metadata_checked_at": "2026-07-12T05:22:19.096Z"
  },
  {
    "id": "ice-2076163747119514036",
    "x_post_id": "2076163747119514036",
    "title": "冰岛执法机构批评释放涉嫌人员延误遣返过程",
    "summary": "一名在拜登政府期间多次被捕的人员因未被及时遣返，相关执法延误被指导致悲剧。",
    "content_type": "brief",
    "published_at": "2026-07-12T04:36:25.000Z",
    "updated_at": "2026-07-12T05:21:06.802Z",
    "url": "/news/ice/2026/07/12/ice-2076163747119514036.html",
    "source_name": "Rose of Sharon Mayer",
    "source_type": "official",
    "agency": "ICE/HSI",
    "source_account": "RozeRage",
    "source_trust": 90,
    "source_url": "https://x.com/RozeRage/status/2076163747119514036",
    "official_url": "",
    "source_text": "@AlanPlotzker @auntbepatriot @David_J_Bier He came over during the Biden administration and had been arrested several times, but he was released each time and officials ignored ICE detainers.\n\nShe would still be alive today had he been deported properly when he was caught the first time. https://t.co/FNsKbvvxZ5",
    "dedupe_key": "text:4b5e1bd5ca75e52185822ef8",
    "image_url": "https://pbs.twimg.com/media/HNAD7B4acAEtIDA.jpg",
    "confidence": 90,
    "keywords": [
      "ICE",
      "遣返",
      "拘留",
      "执法失误"
    ],
    "enforcement_events": [
      {
        "event_type": "arrest",
        "people_count": null,
        "occurred_at": null,
        "time_precision": "unknown",
        "city": "",
        "state_code": "",
        "state_name": "",
        "location_text": "",
        "confidence": 80,
        "source_excerpt": "He came over during the Biden administration and had been arrested several times, but he was released each time and officials ignored ICE detainers."
      }
    ],
    "state_codes": [],
    "event_metadata_checked_at": "2026-07-12T05:21:06.802Z"
  },
  {
    "id": "ice-2076162499792003508",
    "x_post_id": "2076162499792003508",
    "title": "官方未披露具体执法细节 仅确认相关行动态势",
    "summary": "根据官方X账号发布的内容，ICE/HSI相关行动信息有限，未提供详细执法细节。",
    "content_type": "brief",
    "published_at": "2026-07-12T04:31:27.000Z",
    "updated_at": "2026-07-12T05:20:37.903Z",
    "url": "/news/ice/2026/07/12/ice-2076162499792003508.html",
    "source_name": "Cast✿rice",
    "source_type": "official",
    "agency": "ICE/HSI",
    "source_account": "morsflwrs",
    "source_trust": 90,
    "source_url": "https://x.com/morsflwrs/status/2076162499792003508",
    "official_url": "",
    "source_text": "@FloofyEar \"I am happy to have helped you in any way then.  \n\nUpon hearing his words, she felt a little better that he wasn't in much pain, continuing to diligently ice his tail. \n\n\"Oh, ramen?\" \n\nHer eyes sparkled in interest. She has heard of it before though has-",
    "dedupe_key": "text:84289ccc16aa147e5878763c",
    "image_url": "",
    "confidence": 100,
    "keywords": [
      "ICE",
      "HSI",
      "执法",
      "官方发布"
    ],
    "enforcement_events": [],
    "state_codes": [],
    "event_metadata_checked_at": "2026-07-12T05:20:37.903Z"
  },
  {
    "id": "ice-2076161180377153789",
    "x_post_id": "2076161180377153789",
    "title": "康涅狄格州社区支持ICE执法",
    "summary": "康涅狄格州多地社区表达支持ICE执法，认为其必要且受到欢迎。",
    "content_type": "brief",
    "published_at": "2026-07-12T04:26:13.000Z",
    "updated_at": "2026-07-12T05:20:24.711Z",
    "url": "/news/ice/2026/07/12/ice-2076161180377153789.html",
    "source_name": "Let’s Flip CT RED!",
    "source_type": "official",
    "agency": "ICE/HSI",
    "source_account": "NeverBackDownCT",
    "source_trust": 90,
    "source_url": "https://x.com/NeverBackDownCT/status/2076161180377153789",
    "official_url": "",
    "source_text": "@JohnLarsonCT And you are proud to keep criminals on our streets? ICE is needed &amp; wanted in many communities of CT https://t.co/J7l6iowZxv",
    "dedupe_key": "text:54f2f33408a0c9f8567d829a",
    "image_url": "",
    "confidence": 95,
    "keywords": [
      "康涅狄格州",
      "ICE",
      "执法",
      "社区支持"
    ],
    "enforcement_events": [],
    "state_codes": [],
    "event_metadata_checked_at": "2026-07-12T05:20:24.711Z"
  },
  {
    "id": "ice-2076160742588322175",
    "x_post_id": "2076160742588322175",
    "title": "前副警长回忆奥巴马时期ICE执法情况",
    "summary": "一名前副警长表示其在奥巴马总统任内参与过与ICE类似的执法行动，质疑当时为何未见舆论反对。",
    "content_type": "brief",
    "published_at": "2026-07-12T04:24:28.000Z",
    "updated_at": "2026-07-12T05:20:21.215Z",
    "url": "/news/ice/2026/07/12/ice-2076160742588322175.html",
    "source_name": "J (JAWSY) W",
    "source_type": "official",
    "agency": "ICE/HSI",
    "source_account": "WiegersJosh",
    "source_trust": 90,
    "source_url": "https://x.com/WiegersJosh/status/2076160742588322175",
    "official_url": "",
    "source_text": "@JulieanneW68388 I was a Deputy Sheriff and on a task force with ICE during Obama's presidency doing literally the exact same thing ICE is doing today.\nTom Homan was given an award for his deportation efforts. CNN did ride a longs with ICE apprehensions. \nWHERE WAS ALL THE OUTRAGE THEN??????????",
    "dedupe_key": "text:523e3e9ce52db9cd211ea56c",
    "image_url": "",
    "confidence": 90,
    "keywords": [
      "ICE",
      "执法",
      "遣返",
      "奥巴马",
      "特别工作组"
    ],
    "enforcement_events": [],
    "state_codes": [],
    "event_metadata_checked_at": "2026-07-12T05:20:21.215Z"
  },
  {
    "id": "ice-2076160239800357041",
    "x_post_id": "2076160239800357041",
    "title": "ICE官方推特回应有关Khanna被拘留地点质疑",
    "summary": "ICE官方在推特上回应了关于Khanna先生被拘留道路性质的质疑。",
    "content_type": "brief",
    "published_at": "2026-07-12T04:22:29.000Z",
    "updated_at": "2026-07-12T05:20:13.618Z",
    "url": "/news/ice/2026/07/12/ice-2076160239800357041.html",
    "source_name": "Capricornus",
    "source_type": "official",
    "agency": "ICE/HSI",
    "source_account": "Caprico_Uruk",
    "source_trust": 90,
    "source_url": "https://x.com/Caprico_Uruk/status/2076160239800357041",
    "official_url": "",
    "source_text": "@BlueBoxDave Your view is that the road that Mr. Khanna was detained on is analogous to an ICE Facility and that he was there illegally?",
    "dedupe_key": "text:18d6fd6d96414abc96151c9d",
    "image_url": "",
    "confidence": 95,
    "keywords": [
      "ICE",
      "拘留",
      "Khanna",
      "执法"
    ],
    "enforcement_events": [],
    "state_codes": [],
    "event_metadata_checked_at": "2026-07-12T05:20:13.618Z"
  },
  {
    "id": "ice-2076160175761690848",
    "x_post_id": "2076160175761690848",
    "title": "美国联邦检察官与国土安全部副部长会谈推动加州联邦调查",
    "summary": "美国联邦检察官比尔·埃赛利与国土安全部副部长特洛伊·埃德加就加州联邦调查展开富有成效的会谈。",
    "content_type": "brief",
    "published_at": "2026-07-12T04:22:13.000Z",
    "updated_at": "2026-07-12T05:20:10.495Z",
    "url": "/news/ice/2026/07/12/ice-2076160175761690848.html",
    "source_name": "Johnsmith",
    "source_type": "official",
    "agency": "ICE/HSI",
    "source_account": "simswholly",
    "source_trust": 90,
    "source_url": "https://x.com/simswholly/status/2076160175761690848",
    "official_url": "",
    "source_text": "@USAttyEssayli US Attorney Bill Essayli posted about a productive meeting with DHS Deputy Secretary Troy Edgar to discuss advancing federal investigations in California.\n•  Focus areas included prosecutions of those targeting law enforcement, disrupting criminal networks, and boosting",
    "dedupe_key": "text:ee1351bc5c07fa41aee9b839",
    "image_url": "",
    "confidence": 95,
    "keywords": [
      "联邦调查",
      "加州",
      "执法人员",
      "犯罪网络",
      "起诉"
    ],
    "enforcement_events": [],
    "state_codes": [],
    "event_metadata_checked_at": "2026-07-12T05:20:10.495Z"
  },
  {
    "id": "ice-2076160089543627106",
    "x_post_id": "2076160089543627106",
    "title": "ICE官员强调在各地拘留非法移民的执法必要性",
    "summary": "ICE官员表示，无论是否戴面具，他们需要在各地拘留非法入境者。",
    "content_type": "brief",
    "published_at": "2026-07-12T04:21:53.000Z",
    "updated_at": "2026-07-12T05:20:06.359Z",
    "url": "/news/ice/2026/07/12/ice-2076160089543627106.html",
    "source_name": "LockTheMoon2",
    "source_type": "official",
    "agency": "ICE/HSI",
    "source_account": "Moon2Lock84875",
    "source_trust": 90,
    "source_url": "https://x.com/Moon2Lock84875/status/2076160089543627106",
    "official_url": "",
    "source_text": "@RightScopee ICE agents - masked or unmasked- need to be anywhere and everywhere they can take migrants who are illegally in the country into custody.",
    "dedupe_key": "text:39e2bbf9fd21e46afc4d504d",
    "image_url": "",
    "confidence": 90,
    "keywords": [
      "ICE",
      "移民拘留",
      "执法"
    ],
    "enforcement_events": [],
    "state_codes": [],
    "event_metadata_checked_at": "2026-07-12T05:20:06.360Z"
  },
  {
    "id": "ice-2076159259276939289",
    "x_post_id": "2076159259276939289",
    "title": "ICE回应关于逮捕及遣返非法移民的质疑",
    "summary": "ICE针对关于逮捕和遣返非法移民是否构成腐败提出质疑。",
    "content_type": "brief",
    "published_at": "2026-07-12T04:18:35.000Z",
    "updated_at": "2026-07-12T05:19:56.615Z",
    "url": "/news/ice/2026/07/12/ice-2076159259276939289.html",
    "source_name": "Freedom of speech matters",
    "source_type": "official",
    "agency": "ICE/HSI",
    "source_account": "Hump98Clint",
    "source_trust": 90,
    "source_url": "https://x.com/Hump98Clint/status/2076159259276939289",
    "official_url": "",
    "source_text": "@GinaHinojosaTX Do you understand what ICE does? How is it corruption to arrest and deport illegal aliens? Please explain? Or are you just saying words that you like to hear?",
    "dedupe_key": "text:93c7c8c54e6865e0137bbcc4",
    "image_url": "",
    "confidence": 90,
    "keywords": [
      "ICE",
      "逮捕",
      "遣返",
      "非法移民",
      "执法"
    ],
    "enforcement_events": [],
    "state_codes": [],
    "event_metadata_checked_at": "2026-07-12T05:19:56.615Z"
  },
  {
    "id": "ice-2076157024430383245",
    "x_post_id": "2076157024430383245",
    "title": "涉袭击ICE特工事件中人员死亡",
    "summary": "一名涉嫌袭击ICE特工的非法入境者已死亡，事件详情待进一步公布。",
    "content_type": "brief",
    "published_at": "2026-07-12T04:09:42.000Z",
    "updated_at": "2026-07-12T05:19:37.100Z",
    "url": "/news/ice/2026/07/12/ice-2076157024430383245.html",
    "source_name": "1songdog",
    "source_type": "official",
    "agency": "ICE/HSI",
    "source_account": "JasonButle59631",
    "source_trust": 90,
    "source_url": "https://x.com/JasonButle59631/status/2076157024430383245",
    "official_url": "",
    "source_text": "They are criminal illegal aliens..🤷‍♂️and you believed them? 🤣\nLorenzo tried to kill ICE agents and now he is dead. Note to illegals: Self deportation is the answer and if ICE shows up DO NOT threaten them! https://t.co/x4nduTPkN9",
    "dedupe_key": "text:dfce0ac30c66828abd928c2b",
    "image_url": "",
    "confidence": 85,
    "keywords": [
      "ICE",
      "袭击",
      "非法入境者",
      "死亡"
    ],
    "enforcement_events": [
      {
        "event_type": "other",
        "people_count": 1,
        "occurred_at": "2026-07-12T04:09:42.000Z",
        "time_precision": "second",
        "city": "",
        "state_code": "",
        "state_name": "",
        "location_text": "",
        "confidence": 85,
        "source_excerpt": "Lorenzo tried to kill ICE agents and now he is dead."
      }
    ],
    "state_codes": [],
    "event_metadata_checked_at": "2026-07-12T05:19:37.100Z"
  },
  {
    "id": "ice-2076156381053497532",
    "x_post_id": "2076156381053497532",
    "title": "ICE官员明确移民执法职责",
    "summary": "ICE官员在社交媒体上重申移民执法属于执法范围，违法居留者须自愿离境或被遣返。",
    "content_type": "brief",
    "published_at": "2026-07-12T04:07:09.000Z",
    "updated_at": "2026-07-12T05:19:19.599Z",
    "url": "/news/ice/2026/07/12/ice-2076156381053497532.html",
    "source_name": "Bill Smith",
    "source_type": "official",
    "agency": "ICE/HSI",
    "source_account": "BillSmi14630002",
    "source_trust": 90,
    "source_url": "https://x.com/BillSmi14630002/status/2076156381053497532",
    "official_url": "",
    "source_text": "@PramilaJayapal Immigration enforcement is law enforcement, you retard. ICE is enforcing immigration laws. You know, the immigration laws passed by Congress. If you are here illegally then you are breaking the law and need to go, either by self-deporting or being deported.",
    "dedupe_key": "text:187b6f8b5dce9e44c6f0e480",
    "image_url": "",
    "confidence": 100,
    "keywords": [
      "ICE",
      "移民执法",
      "遣返",
      "非法居留"
    ],
    "enforcement_events": [],
    "state_codes": [],
    "event_metadata_checked_at": "2026-07-12T05:19:19.600Z"
  },
  {
    "id": "ice-2075567019064168475",
    "x_post_id": "2075567019064168475",
    "title": "ICE鼓励公众举报可疑活动支持华盛顿特区庆典安全",
    "summary": "美国移民与海关执法局呼吁公众通过热线举报可疑活动，保障国家250周年庆典安全。",
    "content_type": "brief",
    "published_at": "2026-07-10T13:05:14.000Z",
    "updated_at": "2026-07-10T13:23:35.762Z",
    "url": "/news/ice/2026/07/10/ice-2075567019064168475.html",
    "source_name": "美国移民与海关执法局",
    "source_url": "https://x.com/ICEgov/status/2075567019064168475",
    "official_url": "",
    "image_url": "https://pbs.twimg.com/media/HM3lNEAWoAAOGw9.jpg",
    "confidence": 95,
    "keywords": [
      "ICE",
      "举报可疑活动",
      "华盛顿特区",
      "安全",
      "250周年庆典"
    ],
    "enforcement_events": [],
    "state_codes": [],
    "event_metadata_checked_at": "2026-07-10T14:03:53.038Z"
  },
  {
    "id": "ice-2075340524463013910",
    "x_post_id": "2075340524463013910",
    "title": "ICE VOICE办公室为涉移民犯罪受害者及其家庭提供支持",
    "summary": "ICE的VOICE办公室帮助受害者了解执法和遣返流程，并提供自动拘留状态信息订阅服务。",
    "content_type": "brief",
    "published_at": "2026-07-09T22:05:13.000Z",
    "updated_at": "2026-07-10T13:22:55.564Z",
    "url": "/news/ice/2026/07/09/ice-2075340524463013910.html",
    "source_name": "美国移民与海关执法局",
    "source_url": "https://x.com/ICEgov/status/2075340524463013910",
    "official_url": "",
    "image_url": "https://pbs.twimg.com/media/HM0XNWUWMAAtAAN.jpg",
    "confidence": 100,
    "keywords": [
      "ICE",
      "VOICE办公室",
      "移民犯罪",
      "受害者支持",
      "拘留状态"
    ],
    "enforcement_events": [],
    "state_codes": [],
    "event_metadata_checked_at": "2026-07-10T14:03:55.081Z"
  },
  {
    "id": "ice-2075245542930596058",
    "x_post_id": "2075245542930596058",
    "title": "ICE领导打击2026年世界杯前儿童性贩运行动取得多次逮捕和指控",
    "summary": "美国移民与海关执法局HSI总部领导的打击儿童性贩运行动在堪萨斯城2026年世界杯前取得多次逮捕和指控。",
    "content_type": "brief",
    "published_at": "2026-07-09T15:47:48.000Z",
    "updated_at": "2026-07-10T13:23:13.853Z",
    "url": "/news/ice/2026/07/09/ice-2075245542930596058.html",
    "source_name": "美国移民与海关执法局",
    "source_url": "https://x.com/ICEgov/status/2075245542930596058",
    "official_url": "",
    "image_url": "https://pbs.twimg.com/ext_tw_video_thumb/2075245455273865216/pu/img/gTQOf1kOfZnRmn-O.jpg",
    "confidence": 90,
    "keywords": [
      "ICE",
      "HSI",
      "儿童性贩运",
      "逮捕",
      "指控",
      "世界杯2026",
      "堪萨斯城"
    ],
    "enforcement_events": [],
    "state_codes": [],
    "event_metadata_checked_at": "2026-07-10T14:03:56.043Z"
  },
  {
    "id": "ice-2075219680793362937",
    "x_post_id": "2075219680793362937",
    "title": "ICE金边办事处聚焦柬埔寨公民遣返和旅行证件办理",
    "summary": "美国移民与海关执法局金边办事处主要负责柬埔寨公民遣返及旅行证件获取工作。",
    "content_type": "brief",
    "published_at": "2026-07-09T14:05:02.000Z",
    "updated_at": "2026-07-10T13:23:17.334Z",
    "url": "/news/ice/2026/07/09/ice-2075219680793362937.html",
    "source_name": "美国移民与海关执法局",
    "source_url": "https://x.com/ICEgov/status/2075219680793362937",
    "official_url": "",
    "image_url": "https://pbs.twimg.com/ext_tw_video_thumb/2075218490143744000/pu/img/ylO77xXDZOctQbWC.jpg",
    "confidence": 95,
    "keywords": [
      "ICE",
      "遣返",
      "柬埔寨",
      "旅行证件",
      "金边"
    ],
    "enforcement_events": [],
    "state_codes": [],
    "event_metadata_checked_at": "2026-07-10T14:03:57.959Z"
  },
  {
    "id": "ice-2075086308620276035",
    "x_post_id": "2075086308620276035",
    "title": "佛罗里达男子因射杀吉娃娃被指控，ICE对其实施移民扣留",
    "summary": "佛罗里达男子米格尔·雷耶斯·罗德里格斯因自称自卫射杀吉娃娃被指控，ICE对其实施移民扣留。",
    "content_type": "brief",
    "published_at": "2026-07-09T05:15:03.000Z",
    "updated_at": "2026-07-10T13:23:24.545Z",
    "url": "/news/ice/2026/07/09/ice-2075086308620276035.html",
    "source_name": "美国移民与海关执法局",
    "source_url": "https://x.com/ICEgov/status/2075086308620276035",
    "official_url": "",
    "image_url": "https://pbs.twimg.com/ext_tw_video_thumb/2075085098307682304/pu/img/YLZb0XyZgd_rDFWz.jpg",
    "confidence": 95,
    "keywords": [
      "米格尔·雷耶斯·罗德里格斯",
      "佛罗里达",
      "吉娃娃",
      "自卫",
      "指控",
      "移民扣留",
      "非法入境"
    ],
    "enforcement_events": [
      {
        "event_type": "detention",
        "people_count": null,
        "occurred_at": null,
        "time_precision": "unknown",
        "city": "",
        "state_code": "FL",
        "state_name": "Florida",
        "location_text": "佛罗里达",
        "confidence": 100,
        "source_excerpt": "ICE对米格尔·雷耶斯·罗德里格斯实施移民扣留"
      }
    ],
    "state_codes": [
      "FL"
    ],
    "event_metadata_checked_at": "2026-07-10T14:04:03.437Z"
  }
]
